model_inspect/__init__.py
model_inspect/cli.py
model_inspect-0.5.2.dist-info/METADATA
model_inspect-0.5.2.dist-info/WHEEL
model_inspect-0.5.2.dist-info/entry_points.txt
model_inspect-0.5.2.dist-info/top_level.txt
model_inspect-0.5.2.dist-info/RECORD
